replcolor/__init__.py
replcolor-0.0.7.dist-info/LICENSE
replcolor-0.0.7.dist-info/METADATA
replcolor-0.0.7.dist-info/WHEEL
replcolor-0.0.7.dist-info/top_level.txt
replcolor-0.0.7.dist-info/RECORD
