Metadata-Version: 2.1
Name: replcolor
Version: 0.0.7
Summary: rgb colors for replit
Home-page: https://github.com/sk337/replcolor
Author: Nathan T
Author-email: self@dreamclient.us
License: UNKNOWN
Platform: UNKNOWN
Classifier: Programming Language :: Python :: 3
Classifier: License :: OSI Approved :: MIT License
Classifier: Operating System :: OS Independent
Requires-Python: >=3.6
